mappa/__init__.py
mappa/service/__init__.py
mappa/service/mappa_export_service.py
mappa/service/mappa_service.py
tests/exports/__init__.py
tests/exports/test_export_xlsx.py
tests/mocks/__init__.py
tests/mocks/request.py
tests/models/__init__.py
tests/models/mappa/__init__.py
tests/models/mappa/test_response_models.py
tests/models/mappa/test_service.py
escoteiros_mappa-0.1.1.dist-info/LICENSE
escoteiros_mappa-0.1.1.dist-info/METADATA
escoteiros_mappa-0.1.1.dist-info/WHEEL
escoteiros_mappa-0.1.1.dist-info/top_level.txt
escoteiros_mappa-0.1.1.dist-info/zip-safe
escoteiros_mappa-0.1.1.dist-info/RECORD
