Metadata-Version: 2.1
Name: escoteiros-mappa
Version: 0.1.1
Summary: Integração com API mappa
Home-page: https://github.com/guionardo/escoteiros-mappa
Author: Guionardo Furlan
Author-email: guionardo@gmail.com
License: MIT
Project-URL: Documentation, https://github.com/guionardo/escoteiros-mappa/wiki
Project-URL: Source, https://github.com/guionardo/escoteiros-mappa
Keywords: escoteiros scouts mappa
Platform: UNKNOWN
Classifier: Development Status :: 4 - Beta
Classifier: Environment :: Console
Classifier: Intended Audience :: Developers
Classifier: License :: OSI Approved :: MIT License
Classifier: Topic :: Software Development :: Build Tools
Classifier: Topic :: Utilities
Classifier: Programming Language :: Python
Classifier: Programming Language :: Python :: 3.6
Classifier: Programming Language :: Python :: 3.7
Classifier: Programming Language :: Python :: 3.8
Requires-Python: >=3.6.*
Requires-Dist: base-model-guiosoft
Requires-Dist: python-dotenv
Requires-Dist: cache-guiosoft
Requires-Dist: openpyxl
Requires-Dist: orjson
Requires-Dist: python-dateutil
Requires-Dist: requests
